LICENSE
setup.py
kolima/__init__.py
kolima.egg-info/PKG-INFO
kolima.egg-info/SOURCES.txt
kolima.egg-info/dependency_links.txt
kolima.egg-info/requires.txt
kolima.egg-info/top_level.txt