Metadata-Version: 2.1
Name: kolima
Version: 0.0
Summary: ORM-like library for OLAP use cases
Author: B12
License-File: LICENSE
